cx_Oracle.cp312-win_amd64.pyd
cx_Oracle2-8.3.1.data/data/cx_Oracle-doc/LICENSE.txt
cx_Oracle2-8.3.1.data/data/cx_Oracle-doc/README.txt
cx_Oracle2-8.3.1.dist-info/LICENSE.txt
cx_Oracle2-8.3.1.dist-info/METADATA
cx_Oracle2-8.3.1.dist-info/WHEEL
cx_Oracle2-8.3.1.dist-info/top_level.txt
cx_Oracle2-8.3.1.dist-info/RECORD
